pychemcurv/__init__.py
pychemcurv/analysis.py
pychemcurv/core.py
pychemcurv/geometry.py
pychemcurv/version.py
pychemcurv/vis.py
pychemcurv-2022.3.17.dist-info/LICENSE
pychemcurv-2022.3.17.dist-info/METADATA
pychemcurv-2022.3.17.dist-info/WHEEL
pychemcurv-2022.3.17.dist-info/top_level.txt
pychemcurv-2022.3.17.dist-info/RECORD
