Metadata-Version: 2.1
Name: pychemcurv
Version: 2022.3.17
Summary: Discrete and local curvature applied to chemistry and chemical reactivity
Author-email: Julia Sabalot-cuzzubbo <julia.sabalot@gmail.com>, Germain Salvato Vallverdu <germain.vallverdu@univ-pau.fr>, Didier Bégué <didier.begue@univ-pau.fr>, Jacky Cresson <jacky.cresson@univ-pau.fr>
Maintainer-email: Germain Salvato Vallverdu <germain.vallverdu@univ-pau.fr>
License: MIT License
Project-URL: Homepage, https://github.com/gVallverdu/pychemcurv
Project-URL: Bug Tracker, https://github.com/gVallverdu/pychemcurv/issues
Keywords: chemistry,curvature,POAV,hybridation
Classifier: Programming Language :: Python :: 3.9
Classifier: Development Status :: 5 - Production/Stable
Classifier: License :: OSI Approved :: MIT License
Classifier: Operating System :: OS Independent
Classifier: Intended Audience :: Science/Research
Classifier: Topic :: Scientific/Engineering :: Chemistry
Classifier: Topic :: Scientific/Engineering :: Visualization
Requires-Python: >=3.9
License-File: LICENSE
Requires-Dist: numpy
Requires-Dist: pandas
Requires-Dist: pymatgen
Requires-Dist: matplotlib
Requires-Dist: scipy
Provides-Extra: viz
Requires-Dist: ase ; extra == 'viz'
Requires-Dist: jupyter ; extra == 'viz'
Requires-Dist: nglview ; extra == 'viz'
